jacked/__init__.py
jacked/_compatibility_impl.py
jacked/_container.py
jacked/_discover.py
jacked/_exceptions.py
jacked/_inject.py
jacked/_injectable.py
jacked/_typing.py
jacked/matchers/__init__.py
jacked/matchers/_base_matcher.py
jacked/matchers/_callable.py
jacked/matchers/_list.py
jacked/matchers/_object.py
jacked/matchers/_type.py
jacked-1.0.0a3.dist-info/LICENSE
jacked-1.0.0a3.dist-info/METADATA
jacked-1.0.0a3.dist-info/WHEEL
jacked-1.0.0a3.dist-info/top_level.txt
jacked-1.0.0a3.dist-info/RECORD
