Metadata-Version: 2.1
Name: jacked
Version: 1.0.0a3
Summary: Dependency injection for Python
Home-page: https://github.com/ramonhagenaars/jacked
Author: Ramon Hagenaars
Author-email: ramon.hagenaars@gmail.com
License: UNKNOWN
Platform: UNKNOWN
Classifier: Intended Audience :: Developers
Classifier: License :: OSI Approved :: MIT License
Classifier: Operating System :: OS Independent
Classifier: Natural Language :: English
Classifier: Programming Language :: Python
Classifier: Programming Language :: Python :: 3
Classifier: Programming Language :: Python :: 3.5
Classifier: Programming Language :: Python :: 3.6
Classifier: Programming Language :: Python :: 3.7
Classifier: Programming Language :: Python :: 3.8
